sigma/backends/openobserve/__init__.py
sigma/backends/openobserve/openobserve.py
sigma/pipelines/openobserve/kunai.py
sigma/pipelines/openobserve/kunai.yml
sigma/pipelines/openobserve/zeek.py
pysigma_backend_openobserve-0.1.0.dist-info/LICENSE
pysigma_backend_openobserve-0.1.0.dist-info/METADATA
pysigma_backend_openobserve-0.1.0.dist-info/WHEEL
pysigma_backend_openobserve-0.1.0.dist-info/RECORD
