Metadata-Version: 2.3
Name: pySigma-backend-openobserve
Version: 0.1.0
Summary: pySigma openobserve backend
License: LGPL-3.0-only
Author: juju4
Requires-Python: >=3.9,<4.0
Classifier: License :: OSI Approved :: GNU Lesser General Public License v3 (LGPLv3)
Classifier: Programming Language :: Python :: 3
Classifier: Programming Language :: Python :: 3.9
Classifier: Programming Language :: Python :: 3.10
Classifier: Programming Language :: Python :: 3.11
Classifier: Programming Language :: Python :: 3.12
Classifier: Programming Language :: Python :: 3.13
Requires-Dist: pysigma (>=0.11.17,<0.12.0)
Project-URL: Repository, https://github.com/juju4/pySigma-backend-openobserve
